doingscience/__init__.py
doingscience/general_functions.py
doingscience-0.0.1.dist-info/WHEEL
doingscience-0.0.1.dist-info/METADATA
doingscience-0.0.1.dist-info/RECORD
